TimePrint/__init__.py
TimePrintOnPYPI-0.1.0.dist-info/METADATA
TimePrintOnPYPI-0.1.0.dist-info/WHEEL
TimePrintOnPYPI-0.1.0.dist-info/top_level.txt
TimePrintOnPYPI-0.1.0.dist-info/RECORD
