Metadata-Version: 2.1
Name: TimePrintOnPYPI
Version: 0.1.0
Summary: A package for printing text with time delay between characters
Home-page: https://github.com/SForces/TimePrint
Author: Osman TUNA
Author-email: osmntn08@gmail.com
License: MIT
Classifier: Development Status :: 3 - Alpha
Classifier: Intended Audience :: Developers
Classifier: License :: OSI Approved :: MIT License
Classifier: Programming Language :: Python :: 3.9
